genricAlert/__init__.py
genricAlert/emailUtil.py
genricAlert/s3Util.py
genricAlert-0.3.2.dist-info/LICENSE
genricAlert-0.3.2.dist-info/METADATA
genricAlert-0.3.2.dist-info/WHEEL
genricAlert-0.3.2.dist-info/top_level.txt
genricAlert-0.3.2.dist-info/RECORD
