Metadata-Version: 2.1
Name: genricAlert
Version: 0.3.2
Summary: check presence of s3Path, email reports, duplicacy in data and send mail.
Home-page: https://github.com/vikrant462/pypi/genricAlert
Author: vikrant
Author-email: cvikrant462@gmail.com
Project-URL: Bug Tracker, https://github.com/vikrant462/pypi/genricAlert/issues
Classifier: Programming Language :: Python :: 3
Classifier: License :: OSI Approved :: MIT License
Classifier: Operating System :: OS Independent
Requires-Python: >=3.7
License-File: LICENSE
